hivemind_plugin_manager/__init__.py
hivemind_plugin_manager/database.py
hivemind_plugin_manager/protocols.py
hivemind_plugin_manager/tui.py
hivemind_plugin_manager/version.py
hivemind_plugin_manager-0.4.0.dist-info/LICENSE.md
hivemind_plugin_manager-0.4.0.dist-info/METADATA
hivemind_plugin_manager-0.4.0.dist-info/WHEEL
hivemind_plugin_manager-0.4.0.dist-info/entry_points.txt
hivemind_plugin_manager-0.4.0.dist-info/top_level.txt
hivemind_plugin_manager-0.4.0.dist-info/RECORD
