Metadata-Version: 2.1
Name: hivemind-plugin-manager
Version: 0.4.0
Summary: plugin manager for hivemind-core
Home-page: https://github.com/JarbasHiveMind/hivemind-plugin-manager
Author: jarbasAi
Author-email: jarbasai@mailfence.com
License: Apache-2.0
Platform: UNKNOWN
Requires-Dist: json-database
Requires-Dist: ovos-bus-client
Requires-Dist: ovos-utils
